nifc_wildfires/__init__.py
nifc_wildfires/cli.py
nifc_wildfires-0.4.1.dist-info/licenses/LICENSE
nifc_wildfires-0.4.1.dist-info/METADATA
nifc_wildfires-0.4.1.dist-info/WHEEL
nifc_wildfires-0.4.1.dist-info/entry_points.txt
nifc_wildfires-0.4.1.dist-info/top_level.txt
nifc_wildfires-0.4.1.dist-info/RECORD
