Metadata-Version: 2.4
Name: nifc-wildfires
Version: 0.4.1
Summary: Download wildfires data from the National Interagency Fire Center
Author-email: Ben Welsh <b@palewi.re>
License: MIT
Project-URL: Source, https://github.com/datadesk/nifc-wildfires
Project-URL: Tracker, https://github.com/datadesk/nifc-wildfires/issues
Classifier: Development Status :: 5 - Production/Stable
Classifier: Operating System :: OS Independent
Classifier: Intended Audience :: Developers
Classifier: Programming Language :: Python
Classifier: Programming Language :: Python :: 3
Classifier: Programming Language :: Python :: 3.9
Classifier: Programming Language :: Python :: 3.10
Classifier: Programming Language :: Python :: 3.11
Classifier: Programming Language :: Python :: 3.12
Classifier: Programming Language :: Python :: 3.13
Requires-Python: >=3.7
License-File: LICENSE
Requires-Dist: requests
Requires-Dist: click
Provides-Extra: deploy
Requires-Dist: twine; extra == "deploy"
Requires-Dist: wheel; extra == "deploy"
Requires-Dist: pre-commit; extra == "deploy"
Provides-Extra: docs
Requires-Dist: sphinx; extra == "docs"
Requires-Dist: sphinx-autobuild; extra == "docs"
Requires-Dist: sphinx-palewire-theme; extra == "docs"
Requires-Dist: myst-parser; extra == "docs"
Dynamic: license-file
